[
  {
    "sha": "7c2983859b9c06b97e4775abafb07436a15bfe04",
    "node_id": "MDY6Q29tbWl0MTUwNzU3NDU4OjdjMjk4Mzg1OWI5YzA2Yjk3ZTQ3NzVhYmFmYjA3NDM2YTE1YmZlMDQ=",
    "commit": {
      "author": {
        "name": "Tim Usner",
        "email": "tim.usner@sap.com",
        "date": "2018-11-08T07:03:02Z"
      },
      "committer": {
        "name": "Tim Usner",
        "email": "tim.usner@sap.com",
        "date": "2018-11-08T07:03:02Z"
      },
      "message": "Adjust ClusterRole rules for ServiceAccount",
      "tree": {
        "sha": "034695d39fbc2973ce8ba3675402e72c49c051a2",
        "url": "https://api.github.com/repos/gardener/cert-broker/git/trees/034695d39fbc2973ce8ba3675402e72c49c051a2"
      },
      "url": "https://api.github.com/repos/gardener/cert-broker/git/commits/7c2983859b9c06b97e4775abafb07436a15bfe04",
      "comment_count": 0,
      "verification": {
        "verified": false,
        "reason": "unsigned",
        "signature": null,
        "payload": null
      }
    },
    "url": "https://api.github.com/repos/gardener/cert-broker/commits/7c2983859b9c06b97e4775abafb07436a15bfe04",
    "html_url": "https://github.com/gardener/cert-broker/commit/7c2983859b9c06b97e4775abafb07436a15bfe04",
    "comments_url": "https://api.github.com/repos/gardener/cert-broker/commits/7c2983859b9c06b97e4775abafb07436a15bfe04/comments",
    "author": {
      "login": "timuthy",
      "id": 40451181,
      "node_id": "MDQ6VXNlcjQwNDUxMTgx",
      "avatar_url": "https://avatars1.githubusercontent.com/u/40451181?v=4",
      "gravatar_id": "",
      "url": "https://api.github.com/users/timuthy",
      "html_url": "https://github.com/timuthy",
      "followers_url": "https://api.github.com/users/timuthy/followers",
      "following_url": "https://api.github.com/users/timuthy/following{/other_user}",
      "gists_url": "https://api.github.com/users/timuthy/gists{/gist_id}",
      "starred_url": "https://api.github.com/users/timuthy/starred{/owner}{/repo}",
      "subscriptions_url": "https://api.github.com/users/timuthy/subscriptions",
      "organizations_url": "https://api.github.com/users/timuthy/orgs",
      "repos_url": "https://api.github.com/users/timuthy/repos",
      "events_url": "https://api.github.com/users/timuthy/events{/privacy}",
      "received_events_url": "https://api.github.com/users/timuthy/received_events",
      "type": "User",
      "site_admin": false
    },
    "committer": {
      "login": "timuthy",
      "id": 40451181,
      "node_id": "MDQ6VXNlcjQwNDUxMTgx",
      "avatar_url": "https://avatars1.githubusercontent.com/u/40451181?v=4",
      "gravatar_id": "",
      "url": "https://api.github.com/users/timuthy",
      "html_url": "https://github.com/timuthy",
      "followers_url": "https://api.github.com/users/timuthy/followers",
      "following_url": "https://api.github.com/users/timuthy/following{/other_user}",
      "gists_url": "https://api.github.com/users/timuthy/gists{/gist_id}",
      "starred_url": "https://api.github.com/users/timuthy/starred{/owner}{/repo}",
      "subscriptions_url": "https://api.github.com/users/timuthy/subscriptions",
      "organizations_url": "https://api.github.com/users/timuthy/orgs",
      "repos_url": "https://api.github.com/users/timuthy/repos",
      "events_url": "https://api.github.com/users/timuthy/events{/privacy}",
      "received_events_url": "https://api.github.com/users/timuthy/received_events",
      "type": "User",
      "site_admin": false
    },
    "parents": [
      {
        "sha": "ff228fe7e14c6b563a0111446f0fa9bf78fab2c0",
        "url": "https://api.github.com/repos/gardener/cert-broker/commits/ff228fe7e14c6b563a0111446f0fa9bf78fab2c0",
        "html_url": "https://github.com/gardener/cert-broker/commit/ff228fe7e14c6b563a0111446f0fa9bf78fab2c0"
      }
    ]
  },
  {
    "sha": "ff228fe7e14c6b563a0111446f0fa9bf78fab2c0",
    "node_id": "MDY6Q29tbWl0MTUwNzU3NDU4OmZmMjI4ZmU3ZTE0YzZiNTYzYTAxMTE0NDZmMGZhOWJmNzhmYWIyYzA=",
    "commit": {
      "author": {
        "name": "Tim Usner",
        "email": "tim.usner@sap.com",
        "date": "2018-11-05T19:09:51Z"
      },
      "committer": {
        "name": "Tim Usner",
        "email": "tim.usner@sap.com",
        "date": "2018-11-07T08:31:22Z"
      },
      "message": "Add service account and rbac",
      "tree": {
        "sha": "f465167a7221befbed8d64313a72967963f3faaa",
        "url": "https://api.github.com/repos/gardener/cert-broker/git/trees/f465167a7221befbed8d64313a72967963f3faaa"
      },
      "url": "https://api.github.com/repos/gardener/cert-broker/git/commits/ff228fe7e14c6b563a0111446f0fa9bf78fab2c0",
      "comment_count": 0,
      "verification": {
        "verified": false,
        "reason": "unsigned",
        "signature": null,
        "payload": null
      }
    },
    "url": "https://api.github.com/repos/gardener/cert-broker/commits/ff228fe7e14c6b563a0111446f0fa9bf78fab2c0",
    "html_url": "https://github.com/gardener/cert-broker/commit/ff228fe7e14c6b563a0111446f0fa9bf78fab2c0",
    "comments_url": "https://api.github.com/repos/gardener/cert-broker/commits/ff228fe7e14c6b563a0111446f0fa9bf78fab2c0/comments",
    "author": {
      "login": "timuthy",
      "id": 40451181,
      "node_id": "MDQ6VXNlcjQwNDUxMTgx",
      "avatar_url": "https://avatars1.githubusercontent.com/u/40451181?v=4",
      "gravatar_id": "",
      "url": "https://api.github.com/users/timuthy",
      "html_url": "https://github.com/timuthy",
      "followers_url": "https://api.github.com/users/timuthy/followers",
      "following_url": "https://api.github.com/users/timuthy/following{/other_user}",
      "gists_url": "https://api.github.com/users/timuthy/gists{/gist_id}",
      "starred_url": "https://api.github.com/users/timuthy/starred{/owner}{/repo}",
      "subscriptions_url": "https://api.github.com/users/timuthy/subscriptions",
      "organizations_url": "https://api.github.com/users/timuthy/orgs",
      "repos_url": "https://api.github.com/users/timuthy/repos",
      "events_url": "https://api.github.com/users/timuthy/events{/privacy}",
      "received_events_url": "https://api.github.com/users/timuthy/received_events",
      "type": "User",
      "site_admin": false
    },
    "committer": {
      "login": "timuthy",
      "id": 40451181,
      "node_id": "MDQ6VXNlcjQwNDUxMTgx",
      "avatar_url": "https://avatars1.githubusercontent.com/u/40451181?v=4",
      "gravatar_id": "",
      "url": "https://api.github.com/users/timuthy",
      "html_url": "https://github.com/timuthy",
      "followers_url": "https://api.github.com/users/timuthy/followers",
      "following_url": "https://api.github.com/users/timuthy/following{/other_user}",
      "gists_url": "https://api.github.com/users/timuthy/gists{/gist_id}",
      "starred_url": "https://api.github.com/users/timuthy/starred{/owner}{/repo}",
      "subscriptions_url": "https://api.github.com/users/timuthy/subscriptions",
      "organizations_url": "https://api.github.com/users/timuthy/orgs",
      "repos_url": "https://api.github.com/users/timuthy/repos",
      "events_url": "https://api.github.com/users/timuthy/events{/privacy}",
      "received_events_url": "https://api.github.com/users/timuthy/received_events",
      "type": "User",
      "site_admin": false
    },
    "parents": [
      {
        "sha": "b77df9b2b37543d3bb2c2c9e00edf41c9b7bd5fd",
        "url": "https://api.github.com/repos/gardener/cert-broker/commits/b77df9b2b37543d3bb2c2c9e00edf41c9b7bd5fd",
        "html_url": "https://github.com/gardener/cert-broker/commit/b77df9b2b37543d3bb2c2c9e00edf41c9b7bd5fd"
      }
    ]
  },
  {
    "sha": "b77df9b2b37543d3bb2c2c9e00edf41c9b7bd5fd",
    "node_id": "MDY6Q29tbWl0MTUwNzU3NDU4OmI3N2RmOWIyYjM3NTQzZDNiYjJjMmM5ZTAwZWRmNDFjOWI3YmQ1ZmQ=",
    "commit": {
      "author": {
        "name": "Tim Usner",
        "email": "tim.usner@sap.com",
        "date": "2018-10-29T15:24:02Z"
      },
      "committer": {
        "name": "Tim Usner",
        "email": "tim.usner@sap.com",
        "date": "2018-11-05T08:07:23Z"
      },
      "message": "Change Ingress controller to common",
      "tree": {
        "sha": "89f7fb048bad882d9cc40e4f726984b1429ee41d",
        "url": "https://api.github.com/repos/gardener/cert-broker/git/trees/89f7fb048bad882d9cc40e4f726984b1429ee41d"
      },
      "url": "https://api.github.com/repos/gardener/cert-broker/git/commits/b77df9b2b37543d3bb2c2c9e00edf41c9b7bd5fd",
      "comment_count": 0,
      "verification": {
        "verified": false,
        "reason": "unsigned",
        "signature": null,
        "payload": null
      }
    },
    "url": "https://api.github.com/repos/gardener/cert-broker/commits/b77df9b2b37543d3bb2c2c9e00edf41c9b7bd5fd",
    "html_url": "https://github.com/gardener/cert-broker/commit/b77df9b2b37543d3bb2c2c9e00edf41c9b7bd5fd",
    "comments_url": "https://api.github.com/repos/gardener/cert-broker/commits/b77df9b2b37543d3bb2c2c9e00edf41c9b7bd5fd/comments",
    "author": {
      "login": "timuthy",
      "id": 40451181,
      "node_id": "MDQ6VXNlcjQwNDUxMTgx",
      "avatar_url": "https://avatars1.githubusercontent.com/u/40451181?v=4",
      "gravatar_id": "",
      "url": "https://api.github.com/users/timuthy",
      "html_url": "https://github.com/timuthy",
      "followers_url": "https://api.github.com/users/timuthy/followers",
      "following_url": "https://api.github.com/users/timuthy/following{/other_user}",
      "gists_url": "https://api.github.com/users/timuthy/gists{/gist_id}",
      "starred_url": "https://api.github.com/users/timuthy/starred{/owner}{/repo}",
      "subscriptions_url": "https://api.github.com/users/timuthy/subscriptions",
      "organizations_url": "https://api.github.com/users/timuthy/orgs",
      "repos_url": "https://api.github.com/users/timuthy/repos",
      "events_url": "https://api.github.com/users/timuthy/events{/privacy}",
      "received_events_url": "https://api.github.com/users/timuthy/received_events",
      "type": "User",
      "site_admin": false
    },
    "committer": {
      "login": "timuthy",
      "id": 40451181,
      "node_id": "MDQ6VXNlcjQwNDUxMTgx",
      "avatar_url": "https://avatars1.githubusercontent.com/u/40451181?v=4",
      "gravatar_id": "",
      "url": "https://api.github.com/users/timuthy",
      "html_url": "https://github.com/timuthy",
      "followers_url": "https://api.github.com/users/timuthy/followers",
      "following_url": "https://api.github.com/users/timuthy/following{/other_user}",
      "gists_url": "https://api.github.com/users/timuthy/gists{/gist_id}",
      "starred_url": "https://api.github.com/users/timuthy/starred{/owner}{/repo}",
      "subscriptions_url": "https://api.github.com/users/timuthy/subscriptions",
      "organizations_url": "https://api.github.com/users/timuthy/orgs",
      "repos_url": "https://api.github.com/users/timuthy/repos",
      "events_url": "https://api.github.com/users/timuthy/events{/privacy}",
      "received_events_url": "https://api.github.com/users/timuthy/received_events",
      "type": "User",
      "site_admin": false
    },
    "parents": [
      {
        "sha": "147e5d86782058313676324621ac28f04fc28536",
        "url": "https://api.github.com/repos/gardener/cert-broker/commits/147e5d86782058313676324621ac28f04fc28536",
        "html_url": "https://github.com/gardener/cert-broker/commit/147e5d86782058313676324621ac28f04fc28536"
      }
    ]
  },
  {
    "sha": "147e5d86782058313676324621ac28f04fc28536",
    "node_id": "MDY6Q29tbWl0MTUwNzU3NDU4OjE0N2U1ZDg2NzgyMDU4MzEzNjc2MzI0NjIxYWMyOGYwNGZjMjg1MzY=",
    "commit": {
      "author": {
        "name": "Tim Usner",
        "email": "tim.usner@sap.com",
        "date": "2018-10-29T13:21:18Z"
      },
      "committer": {
        "name": "Tim Usner",
        "email": "tim.usner@sap.com",
        "date": "2018-10-29T13:21:18Z"
      },
      "message": "Let Cert-Broker handle multiple DNS01 providers",
      "tree": {
        "sha": "93d054995100ae329e858b250b34ac1a8f34cfea",
        "url": "https://api.github.com/repos/gardener/cert-broker/git/trees/93d054995100ae329e858b250b34ac1a8f34cfea"
      },
      "url": "https://api.github.com/repos/gardener/cert-broker/git/commits/147e5d86782058313676324621ac28f04fc28536",
      "comment_count": 0,
      "verification": {
        "verified": false,
        "reason": "unsigned",
        "signature": null,
        "payload": null
      }
    },
    "url": "https://api.github.com/repos/gardener/cert-broker/commits/147e5d86782058313676324621ac28f04fc28536",
    "html_url": "https://github.com/gardener/cert-broker/commit/147e5d86782058313676324621ac28f04fc28536",
    "comments_url": "https://api.github.com/repos/gardener/cert-broker/commits/147e5d86782058313676324621ac28f04fc28536/comments",
    "author": {
      "login": "timuthy",
      "id": 40451181,
      "node_id": "MDQ6VXNlcjQwNDUxMTgx",
      "avatar_url": "https://avatars1.githubusercontent.com/u/40451181?v=4",
      "gravatar_id": "",
      "url": "https://api.github.com/users/timuthy",
      "html_url": "https://github.com/timuthy",
      "followers_url": "https://api.github.com/users/timuthy/followers",
      "following_url": "https://api.github.com/users/timuthy/following{/other_user}",
      "gists_url": "https://api.github.com/users/timuthy/gists{/gist_id}",
      "starred_url": "https://api.github.com/users/timuthy/starred{/owner}{/repo}",
      "subscriptions_url": "https://api.github.com/users/timuthy/subscriptions",
      "organizations_url": "https://api.github.com/users/timuthy/orgs",
      "repos_url": "https://api.github.com/users/timuthy/repos",
      "events_url": "https://api.github.com/users/timuthy/events{/privacy}",
      "received_events_url": "https://api.github.com/users/timuthy/received_events",
      "type": "User",
      "site_admin": false
    },
    "committer": {
      "login": "timuthy",
      "id": 40451181,
      "node_id": "MDQ6VXNlcjQwNDUxMTgx",
      "avatar_url": "https://avatars1.githubusercontent.com/u/40451181?v=4",
      "gravatar_id": "",
      "url": "https://api.github.com/users/timuthy",
      "html_url": "https://github.com/timuthy",
      "followers_url": "https://api.github.com/users/timuthy/followers",
      "following_url": "https://api.github.com/users/timuthy/following{/other_user}",
      "gists_url": "https://api.github.com/users/timuthy/gists{/gist_id}",
      "starred_url": "https://api.github.com/users/timuthy/starred{/owner}{/repo}",
      "subscriptions_url": "https://api.github.com/users/timuthy/subscriptions",
      "organizations_url": "https://api.github.com/users/timuthy/orgs",
      "repos_url": "https://api.github.com/users/timuthy/repos",
      "events_url": "https://api.github.com/users/timuthy/events{/privacy}",
      "received_events_url": "https://api.github.com/users/timuthy/received_events",
      "type": "User",
      "site_admin": false
    },
    "parents": [
      {
        "sha": "fda7129db4bcd13149c25d553fcc52c40908b8c2",
        "url": "https://api.github.com/repos/gardener/cert-broker/commits/fda7129db4bcd13149c25d553fcc52c40908b8c2",
        "html_url": "https://github.com/gardener/cert-broker/commit/fda7129db4bcd13149c25d553fcc52c40908b8c2"
      }
    ]
  },
  {
    "sha": "e1794e99ee3a68c9d3df50593ab506c7276531b8",
    "node_id": "MDY6Q29tbWl0MTUwNzU3NDU4OmUxNzk0ZTk5ZWUzYTY4YzlkM2RmNTA1OTNhYjUwNmM3Mjc2NTMxYjg=",
    "commit": {
      "author": {
        "name": "Tim Usner",
        "email": "40451181+timuthy@users.noreply.github.com",
        "date": "2018-10-19T15:25:45Z"
      },
      "committer": {
        "name": "GitHub",
        "email": "noreply@github.com",
        "date": "2018-10-19T15:25:45Z"
      },
      "message": "Update README.md",
      "tree": {
        "sha": "23867bcd2b5f032e04c1d7e8b9546e8aa4879379",
        "url": "https://api.github.com/repos/gardener/cert-broker/git/trees/23867bcd2b5f032e04c1d7e8b9546e8aa4879379"
      },
      "url": "https://api.github.com/repos/gardener/cert-broker/git/commits/e1794e99ee3a68c9d3df50593ab506c7276531b8",
      "comment_count": 0,
      "verification": {
        "verified": true,
        "reason": "valid",
        "signature": "-----BEGIN PGP SIGNATURE-----\n\nwsBcBAABCAAQBQJbyfd5CRBK7hj4Ov3rIwAAdHIIABX55L9sB2gaGmnQNZqsj6ja\nHUZeNAD8p7QP9OCBcsAKe3HaZytebXBMYNj2ZdyytX52Ys8+OiD/pLbLWjh/OEQD\nU8Kvs8JQSVFe1VACcBdOwWSS0ZyP19NTG1v2G9IQnNVdLkDzmWLd9WvMgq/7t6kh\nL8JGlA1yZUKDOKotiSXlUwjU4IUfMbTN75ssP5y7O6YE7leAWQyVagr4u5tuSnCb\n1iypAsRB7VQpvbcK++lKdqXKnzqUaCo1CUh+uvvOU8wE/vqWa3Vp7Hru5CyB50SG\nytrh55TGsKvH9KwKB7InwI/3MRhlZpKovd0voMhITwQ5bFaQNj1NFN7SxDCPDks=\n=mFMp\n-----END PGP SIGNATURE-----\n",
        "payload": "tree 23867bcd2b5f032e04c1d7e8b9546e8aa4879379\nparent a72539e367fd75d47676902e97b7aded0f6d687d\nauthor Tim Usner <40451181+timuthy@users.noreply.github.com> 1539962745 +0200\ncommitter GitHub <noreply@github.com> 1539962745 +0200\n\nUpdate README.md"
      }
    },
    "url": "https://api.github.com/repos/gardener/cert-broker/commits/e1794e99ee3a68c9d3df50593ab506c7276531b8",
    "html_url": "https://github.com/gardener/cert-broker/commit/e1794e99ee3a68c9d3df50593ab506c7276531b8",
    "comments_url": "https://api.github.com/repos/gardener/cert-broker/commits/e1794e99ee3a68c9d3df50593ab506c7276531b8/comments",
    "author": {
      "login": "timuthy",
      "id": 40451181,
      "node_id": "MDQ6VXNlcjQwNDUxMTgx",
      "avatar_url": "https://avatars1.githubusercontent.com/u/40451181?v=4",
      "gravatar_id": "",
      "url": "https://api.github.com/users/timuthy",
      "html_url": "https://github.com/timuthy",
      "followers_url": "https://api.github.com/users/timuthy/followers",
      "following_url": "https://api.github.com/users/timuthy/following{/other_user}",
      "gists_url": "https://api.github.com/users/timuthy/gists{/gist_id}",
      "starred_url": "https://api.github.com/users/timuthy/starred{/owner}{/repo}",
      "subscriptions_url": "https://api.github.com/users/timuthy/subscriptions",
      "organizations_url": "https://api.github.com/users/timuthy/orgs",
      "repos_url": "https://api.github.com/users/timuthy/repos",
      "events_url": "https://api.github.com/users/timuthy/events{/privacy}",
      "received_events_url": "https://api.github.com/users/timuthy/received_events",
      "type": "User",
      "site_admin": false
    },
    "committer": {
      "login": "web-flow",
      "id": 19864447,
      "node_id": "MDQ6VXNlcjE5ODY0NDQ3",
      "avatar_url": "https://avatars3.githubusercontent.com/u/19864447?v=4",
      "gravatar_id": "",
      "url": "https://api.github.com/users/web-flow",
      "html_url": "https://github.com/web-flow",
      "followers_url": "https://api.github.com/users/web-flow/followers",
      "following_url": "https://api.github.com/users/web-flow/following{/other_user}",
      "gists_url": "https://api.github.com/users/web-flow/gists{/gist_id}",
      "starred_url": "https://api.github.com/users/web-flow/starred{/owner}{/repo}",
      "subscriptions_url": "https://api.github.com/users/web-flow/subscriptions",
      "organizations_url": "https://api.github.com/users/web-flow/orgs",
      "repos_url": "https://api.github.com/users/web-flow/repos",
      "events_url": "https://api.github.com/users/web-flow/events{/privacy}",
      "received_events_url": "https://api.github.com/users/web-flow/received_events",
      "type": "User",
      "site_admin": false
    },
    "parents": [
      {
        "sha": "a72539e367fd75d47676902e97b7aded0f6d687d",
        "url": "https://api.github.com/repos/gardener/cert-broker/commits/a72539e367fd75d47676902e97b7aded0f6d687d",
        "html_url": "https://github.com/gardener/cert-broker/commit/a72539e367fd75d47676902e97b7aded0f6d687d"
      }
    ]
  },
  {
    "sha": "5d218faac8348b3b420356a767d5c2fb881de35c",
    "node_id": "MDY6Q29tbWl0MTUwNzU3NDU4OjVkMjE4ZmFhYzgzNDhiM2I0MjAzNTZhNzY3ZDVjMmZiODgxZGUzNWM=",
    "commit": {
      "author": {
        "name": "Tim Usner",
        "email": "tim.usner@sap.com",
        "date": "2018-09-28T14:58:57Z"
      },
      "committer": {
        "name": "Matthias Sohn",
        "email": "matthias.sohn@sap.com",
        "date": "2018-09-28T14:59:59Z"
      },
      "message": "Initial implementation of cert-broker\n\nCert-Broker is a complementary component for Cert-Manager [1].\nIt enables certificate management for Kubernetes clusters which don't\noperate their own (in-cluster) Cert-Manager, e.g. for organizational\nresposibilities the Cert-Manager is located in another cluster.\n\n[1] https://github.com/jetstack/cert-manager\n\nThis is the initial contribution to the Open Source Gardener project.\n\nThe following SAP developers contributed to this project until this\ninitial contribution was published as open source:\n\n$ git shortlog -s -n\n    41  Tim Usner\n     3  Matthias Sohn\n\nIt is derived from the historical, SAP internal cert-broker repository\nat commit ff98b41fe66809ca9ec59f420482c243c6013bba.",
      "tree": {
        "sha": "ae6a8df97f9877a8aa4e9111b1ba36f8e01cc78b",
        "url": "https://api.github.com/repos/gardener/cert-broker/git/trees/ae6a8df97f9877a8aa4e9111b1ba36f8e01cc78b"
      },
      "url": "https://api.github.com/repos/gardener/cert-broker/git/commits/5d218faac8348b3b420356a767d5c2fb881de35c",
      "comment_count": 0,
      "verification": {
        "verified": false,
        "reason": "unsigned",
        "signature": null,
        "payload": null
      }
    },
    "url": "https://api.github.com/repos/gardener/cert-broker/commits/5d218faac8348b3b420356a767d5c2fb881de35c",
    "html_url": "https://github.com/gardener/cert-broker/commit/5d218faac8348b3b420356a767d5c2fb881de35c",
    "comments_url": "https://api.github.com/repos/gardener/cert-broker/commits/5d218faac8348b3b420356a767d5c2fb881de35c/comments",
    "author": {
      "login": "timuthy",
      "id": 40451181,
      "node_id": "MDQ6VXNlcjQwNDUxMTgx",
      "avatar_url": "https://avatars1.githubusercontent.com/u/40451181?v=4",
      "gravatar_id": "",
      "url": "https://api.github.com/users/timuthy",
      "html_url": "https://github.com/timuthy",
      "followers_url": "https://api.github.com/users/timuthy/followers",
      "following_url": "https://api.github.com/users/timuthy/following{/other_user}",
      "gists_url": "https://api.github.com/users/timuthy/gists{/gist_id}",
      "starred_url": "https://api.github.com/users/timuthy/starred{/owner}{/repo}",
      "subscriptions_url": "https://api.github.com/users/timuthy/subscriptions",
      "organizations_url": "https://api.github.com/users/timuthy/orgs",
      "repos_url": "https://api.github.com/users/timuthy/repos",
      "events_url": "https://api.github.com/users/timuthy/events{/privacy}",
      "received_events_url": "https://api.github.com/users/timuthy/received_events",
      "type": "User",
      "site_admin": false
    },
    "committer": {
      "login": "msohn",
      "id": 143355,
      "node_id": "MDQ6VXNlcjE0MzM1NQ==",
      "avatar_url": "https://avatars0.githubusercontent.com/u/143355?v=4",
      "gravatar_id": "",
      "url": "https://api.github.com/users/msohn",
      "html_url": "https://github.com/msohn",
      "followers_url": "https://api.github.com/users/msohn/followers",
      "following_url": "https://api.github.com/users/msohn/following{/other_user}",
      "gists_url": "https://api.github.com/users/msohn/gists{/gist_id}",
      "starred_url": "https://api.github.com/users/msohn/starred{/owner}{/repo}",
      "subscriptions_url": "https://api.github.com/users/msohn/subscriptions",
      "organizations_url": "https://api.github.com/users/msohn/orgs",
      "repos_url": "https://api.github.com/users/msohn/repos",
      "events_url": "https://api.github.com/users/msohn/events{/privacy}",
      "received_events_url": "https://api.github.com/users/msohn/received_events",
      "type": "User",
      "site_admin": false
    },
    "parents": []
  }
]