[
  {
    "sha": "553ae2954cdbf82c406728ec825e344785767fcc",
    "node_id": "MDY6Q29tbWl0MTE2NDI5NDAxOjU1M2FlMjk1NGNkYmY4MmM0MDY3MjhlYzgyNWUzNDQ3ODU3NjdmY2M=",
    "commit": {
      "author": {
        "name": "dherman",
        "email": "daniel.c.herman@gmail.com",
        "date": "2019-01-25T11:12:59Z"
      },
      "committer": {
        "name": "Andreas Fritzler",
        "email": "afritzler@users.noreply.github.com",
        "date": "2019-01-25T11:12:59Z"
      },
      "message": "Correct the spelling of Terraform (#62)\n\nMerged!",
      "tree": {
        "sha": "89dc258abc3170d0b27df3571ee32f41207fc7ff",
        "url": "https://api.github.com/repos/gardener/kubify/git/trees/89dc258abc3170d0b27df3571ee32f41207fc7ff"
      },
      "url": "https://api.github.com/repos/gardener/kubify/git/commits/553ae2954cdbf82c406728ec825e344785767fcc",
      "comment_count": 0,
      "verification": {
        "verified": false,
        "reason": "unsigned",
        "signature": null,
        "payload": null
      }
    },
    "url": "https://api.github.com/repos/gardener/kubify/commits/553ae2954cdbf82c406728ec825e344785767fcc",
    "html_url": "https://github.com/gardener/kubify/commit/553ae2954cdbf82c406728ec825e344785767fcc",
    "comments_url": "https://api.github.com/repos/gardener/kubify/commits/553ae2954cdbf82c406728ec825e344785767fcc/comments",
    "author": {
      "login": "dcherman",
      "id": 976608,
      "node_id": "MDQ6VXNlcjk3NjYwOA==",
      "avatar_url": "https://avatars0.githubusercontent.com/u/976608?v=4",
      "gravatar_id": "",
      "url": "https://api.github.com/users/dcherman",
      "html_url": "https://github.com/dcherman",
      "followers_url": "https://api.github.com/users/dcherman/followers",
      "following_url": "https://api.github.com/users/dcherman/following{/other_user}",
      "gists_url": "https://api.github.com/users/dcherman/gists{/gist_id}",
      "starred_url": "https://api.github.com/users/dcherman/starred{/owner}{/repo}",
      "subscriptions_url": "https://api.github.com/users/dcherman/subscriptions",
      "organizations_url": "https://api.github.com/users/dcherman/orgs",
      "repos_url": "https://api.github.com/users/dcherman/repos",
      "events_url": "https://api.github.com/users/dcherman/events{/privacy}",
      "received_events_url": "https://api.github.com/users/dcherman/received_events",
      "type": "User",
      "site_admin": false
    },
    "committer": {
      "login": "afritzler",
      "id": 1922939,
      "node_id": "MDQ6VXNlcjE5MjI5Mzk=",
      "avatar_url": "https://avatars2.githubusercontent.com/u/1922939?v=4",
      "gravatar_id": "",
      "url": "https://api.github.com/users/afritzler",
      "html_url": "https://github.com/afritzler",
      "followers_url": "https://api.github.com/users/afritzler/followers",
      "following_url": "https://api.github.com/users/afritzler/following{/other_user}",
      "gists_url": "https://api.github.com/users/afritzler/gists{/gist_id}",
      "starred_url": "https://api.github.com/users/afritzler/starred{/owner}{/repo}",
      "subscriptions_url": "https://api.github.com/users/afritzler/subscriptions",
      "organizations_url": "https://api.github.com/users/afritzler/orgs",
      "repos_url": "https://api.github.com/users/afritzler/repos",
      "events_url": "https://api.github.com/users/afritzler/events{/privacy}",
      "received_events_url": "https://api.github.com/users/afritzler/received_events",
      "type": "User",
      "site_admin": false
    },
    "parents": [
      {
        "sha": "7876b13e17118a7600161c7c63f0c13fd07e90fa",
        "url": "https://api.github.com/repos/gardener/kubify/commits/7876b13e17118a7600161c7c63f0c13fd07e90fa",
        "html_url": "https://github.com/gardener/kubify/commit/7876b13e17118a7600161c7c63f0c13fd07e90fa"
      }
    ]
  },
  {
    "sha": "9a06e4d623be98aeca8b7fd7c5e19dab2198f722",
    "node_id": "MDY6Q29tbWl0MTE2NDI5NDAxOjlhMDZlNGQ2MjNiZTk4YWVjYThiN2ZkN2M1ZTE5ZGFiMjE5OGY3MjI=",
    "commit": {
      "author": {
        "name": "Andreas Fritzler",
        "email": "andreas.fritzler@sap.com",
        "date": "2019-01-11T11:21:55Z"
      },
      "committer": {
        "name": "Andreas Fritzler",
        "email": "andreas.fritzler@sap.com",
        "date": "2019-01-11T11:21:55Z"
      },
      "message": "Added support for Kuberenetes v1.10.12",
      "tree": {
        "sha": "98a1e58beafbdb70cade010dbf80a9f076b68619",
        "url": "https://api.github.com/repos/gardener/kubify/git/trees/98a1e58beafbdb70cade010dbf80a9f076b68619"
      },
      "url": "https://api.github.com/repos/gardener/kubify/git/commits/9a06e4d623be98aeca8b7fd7c5e19dab2198f722",
      "comment_count": 0,
      "verification": {
        "verified": false,
        "reason": "unsigned",
        "signature": null,
        "payload": null
      }
    },
    "url": "https://api.github.com/repos/gardener/kubify/commits/9a06e4d623be98aeca8b7fd7c5e19dab2198f722",
    "html_url": "https://github.com/gardener/kubify/commit/9a06e4d623be98aeca8b7fd7c5e19dab2198f722",
    "comments_url": "https://api.github.com/repos/gardener/kubify/commits/9a06e4d623be98aeca8b7fd7c5e19dab2198f722/comments",
    "author": {
      "login": "afritzler",
      "id": 1922939,
      "node_id": "MDQ6VXNlcjE5MjI5Mzk=",
      "avatar_url": "https://avatars2.githubusercontent.com/u/1922939?v=4",
      "gravatar_id": "",
      "url": "https://api.github.com/users/afritzler",
      "html_url": "https://github.com/afritzler",
      "followers_url": "https://api.github.com/users/afritzler/followers",
      "following_url": "https://api.github.com/users/afritzler/following{/other_user}",
      "gists_url": "https://api.github.com/users/afritzler/gists{/gist_id}",
      "starred_url": "https://api.github.com/users/afritzler/starred{/owner}{/repo}",
      "subscriptions_url": "https://api.github.com/users/afritzler/subscriptions",
      "organizations_url": "https://api.github.com/users/afritzler/orgs",
      "repos_url": "https://api.github.com/users/afritzler/repos",
      "events_url": "https://api.github.com/users/afritzler/events{/privacy}",
      "received_events_url": "https://api.github.com/users/afritzler/received_events",
      "type": "User",
      "site_admin": false
    },
    "committer": {
      "login": "afritzler",
      "id": 1922939,
      "node_id": "MDQ6VXNlcjE5MjI5Mzk=",
      "avatar_url": "https://avatars2.githubusercontent.com/u/1922939?v=4",
      "gravatar_id": "",
      "url": "https://api.github.com/users/afritzler",
      "html_url": "https://github.com/afritzler",
      "followers_url": "https://api.github.com/users/afritzler/followers",
      "following_url": "https://api.github.com/users/afritzler/following{/other_user}",
      "gists_url": "https://api.github.com/users/afritzler/gists{/gist_id}",
      "starred_url": "https://api.github.com/users/afritzler/starred{/owner}{/repo}",
      "subscriptions_url": "https://api.github.com/users/afritzler/subscriptions",
      "organizations_url": "https://api.github.com/users/afritzler/orgs",
      "repos_url": "https://api.github.com/users/afritzler/repos",
      "events_url": "https://api.github.com/users/afritzler/events{/privacy}",
      "received_events_url": "https://api.github.com/users/afritzler/received_events",
      "type": "User",
      "site_admin": false
    },
    "parents": [
      {
        "sha": "704291e103aaa5cadbe315cf008114b8601dda63",
        "url": "https://api.github.com/repos/gardener/kubify/commits/704291e103aaa5cadbe315cf008114b8601dda63",
        "html_url": "https://github.com/gardener/kubify/commit/704291e103aaa5cadbe315cf008114b8601dda63"
      }
    ]
  },
  {
    "sha": "6fe63b7c5da3ecb4759276cf414cae0e1494940c",
    "node_id": "MDY6Q29tbWl0MTE2NDI5NDAxOjZmZTYzYjdjNWRhM2VjYjQ3NTkyNzZjZjQxNGNhZTBlMTQ5NDk0MGM=",
    "commit": {
      "author": {
        "name": "Andreas Fritzler",
        "email": "andreas.fritzler@gmail.com",
        "date": "2018-11-05T16:18:58Z"
      },
      "committer": {
        "name": "Andreas Fritzler",
        "email": "andreas.fritzler@gmail.com",
        "date": "2018-11-05T16:18:58Z"
      },
      "message": "Fixed main documentation link and .gitignore",
      "tree": {
        "sha": "7f79487cd4fd97675133e7c3eb5909d7ed8fede3",
        "url": "https://api.github.com/repos/gardener/kubify/git/trees/7f79487cd4fd97675133e7c3eb5909d7ed8fede3"
      },
      "url": "https://api.github.com/repos/gardener/kubify/git/commits/6fe63b7c5da3ecb4759276cf414cae0e1494940c",
      "comment_count": 0,
      "verification": {
        "verified": false,
        "reason": "unsigned",
        "signature": null,
        "payload": null
      }
    },
    "url": "https://api.github.com/repos/gardener/kubify/commits/6fe63b7c5da3ecb4759276cf414cae0e1494940c",
    "html_url": "https://github.com/gardener/kubify/commit/6fe63b7c5da3ecb4759276cf414cae0e1494940c",
    "comments_url": "https://api.github.com/repos/gardener/kubify/commits/6fe63b7c5da3ecb4759276cf414cae0e1494940c/comments",
    "author": {
      "login": "afritzler",
      "id": 1922939,
      "node_id": "MDQ6VXNlcjE5MjI5Mzk=",
      "avatar_url": "https://avatars2.githubusercontent.com/u/1922939?v=4",
      "gravatar_id": "",
      "url": "https://api.github.com/users/afritzler",
      "html_url": "https://github.com/afritzler",
      "followers_url": "https://api.github.com/users/afritzler/followers",
      "following_url": "https://api.github.com/users/afritzler/following{/other_user}",
      "gists_url": "https://api.github.com/users/afritzler/gists{/gist_id}",
      "starred_url": "https://api.github.com/users/afritzler/starred{/owner}{/repo}",
      "subscriptions_url": "https://api.github.com/users/afritzler/subscriptions",
      "organizations_url": "https://api.github.com/users/afritzler/orgs",
      "repos_url": "https://api.github.com/users/afritzler/repos",
      "events_url": "https://api.github.com/users/afritzler/events{/privacy}",
      "received_events_url": "https://api.github.com/users/afritzler/received_events",
      "type": "User",
      "site_admin": false
    },
    "committer": {
      "login": "afritzler",
      "id": 1922939,
      "node_id": "MDQ6VXNlcjE5MjI5Mzk=",
      "avatar_url": "https://avatars2.githubusercontent.com/u/1922939?v=4",
      "gravatar_id": "",
      "url": "https://api.github.com/users/afritzler",
      "html_url": "https://github.com/afritzler",
      "followers_url": "https://api.github.com/users/afritzler/followers",
      "following_url": "https://api.github.com/users/afritzler/following{/other_user}",
      "gists_url": "https://api.github.com/users/afritzler/gists{/gist_id}",
      "starred_url": "https://api.github.com/users/afritzler/starred{/owner}{/repo}",
      "subscriptions_url": "https://api.github.com/users/afritzler/subscriptions",
      "organizations_url": "https://api.github.com/users/afritzler/orgs",
      "repos_url": "https://api.github.com/users/afritzler/repos",
      "events_url": "https://api.github.com/users/afritzler/events{/privacy}",
      "received_events_url": "https://api.github.com/users/afritzler/received_events",
      "type": "User",
      "site_admin": false
    },
    "parents": [
      {
        "sha": "183103da80e361b910d5d354e407cb3437512dcf",
        "url": "https://api.github.com/repos/gardener/kubify/commits/183103da80e361b910d5d354e407cb3437512dcf",
        "html_url": "https://github.com/gardener/kubify/commit/183103da80e361b910d5d354e407cb3437512dcf"
      }
    ]
  },
  {
    "sha": "183103da80e361b910d5d354e407cb3437512dcf",
    "node_id": "MDY6Q29tbWl0MTE2NDI5NDAxOjE4MzEwM2RhODBlMzYxYjkxMGQ1ZDM1NGU0MDdjYjM0Mzc1MTJkY2Y=",
    "commit": {
      "author": {
        "name": "Andreas Fritzler",
        "email": "andreas.fritzler@gmail.com",
        "date": "2018-10-29T13:24:22Z"
      },
      "committer": {
        "name": "Andreas Fritzler",
        "email": "andreas.fritzler@gmail.com",
        "date": "2018-10-29T13:24:22Z"
      },
      "message": "Restructured documentation and landing page",
      "tree": {
        "sha": "9eb9027f8ee4f17461e783c6951036753e5b0e3c",
        "url": "https://api.github.com/repos/gardener/kubify/git/trees/9eb9027f8ee4f17461e783c6951036753e5b0e3c"
      },
      "url": "https://api.github.com/repos/gardener/kubify/git/commits/183103da80e361b910d5d354e407cb3437512dcf",
      "comment_count": 0,
      "verification": {
        "verified": false,
        "reason": "unsigned",
        "signature": null,
        "payload": null
      }
    },
    "url": "https://api.github.com/repos/gardener/kubify/commits/183103da80e361b910d5d354e407cb3437512dcf",
    "html_url": "https://github.com/gardener/kubify/commit/183103da80e361b910d5d354e407cb3437512dcf",
    "comments_url": "https://api.github.com/repos/gardener/kubify/commits/183103da80e361b910d5d354e407cb3437512dcf/comments",
    "author": {
      "login": "afritzler",
      "id": 1922939,
      "node_id": "MDQ6VXNlcjE5MjI5Mzk=",
      "avatar_url": "https://avatars2.githubusercontent.com/u/1922939?v=4",
      "gravatar_id": "",
      "url": "https://api.github.com/users/afritzler",
      "html_url": "https://github.com/afritzler",
      "followers_url": "https://api.github.com/users/afritzler/followers",
      "following_url": "https://api.github.com/users/afritzler/following{/other_user}",
      "gists_url": "https://api.github.com/users/afritzler/gists{/gist_id}",
      "starred_url": "https://api.github.com/users/afritzler/starred{/owner}{/repo}",
      "subscriptions_url": "https://api.github.com/users/afritzler/subscriptions",
      "organizations_url": "https://api.github.com/users/afritzler/orgs",
      "repos_url": "https://api.github.com/users/afritzler/repos",
      "events_url": "https://api.github.com/users/afritzler/events{/privacy}",
      "received_events_url": "https://api.github.com/users/afritzler/received_events",
      "type": "User",
      "site_admin": false
    },
    "committer": {
      "login": "afritzler",
      "id": 1922939,
      "node_id": "MDQ6VXNlcjE5MjI5Mzk=",
      "avatar_url": "https://avatars2.githubusercontent.com/u/1922939?v=4",
      "gravatar_id": "",
      "url": "https://api.github.com/users/afritzler",
      "html_url": "https://github.com/afritzler",
      "followers_url": "https://api.github.com/users/afritzler/followers",
      "following_url": "https://api.github.com/users/afritzler/following{/other_user}",
      "gists_url": "https://api.github.com/users/afritzler/gists{/gist_id}",
      "starred_url": "https://api.github.com/users/afritzler/starred{/owner}{/repo}",
      "subscriptions_url": "https://api.github.com/users/afritzler/subscriptions",
      "organizations_url": "https://api.github.com/users/afritzler/orgs",
      "repos_url": "https://api.github.com/users/afritzler/repos",
      "events_url": "https://api.github.com/users/afritzler/events{/privacy}",
      "received_events_url": "https://api.github.com/users/afritzler/received_events",
      "type": "User",
      "site_admin": false
    },
    "parents": [
      {
        "sha": "d810fb68e1909a4ff0ff5129e4dc02f1e77bbf99",
        "url": "https://api.github.com/repos/gardener/kubify/commits/d810fb68e1909a4ff0ff5129e4dc02f1e77bbf99",
        "html_url": "https://github.com/gardener/kubify/commit/d810fb68e1909a4ff0ff5129e4dc02f1e77bbf99"
      }
    ]
  },
  {
    "sha": "cd11606920cd4988e3d7a4f65d68932b061fc9ea",
    "node_id": "MDY6Q29tbWl0MTE2NDI5NDAxOmNkMTE2MDY5MjBjZDQ5ODhlM2Q3YTRmNjVkNjg5MzJiMDYxZmM5ZWE=",
    "commit": {
      "author": {
        "name": "Uwe Krueger",
        "email": "uwe.krueger@sap.com",
        "date": "2018-05-23T13:03:29Z"
      },
      "committer": {
        "name": "Andreas Fritzler",
        "email": "andreas.fritzler@sap.com",
        "date": "2018-10-16T15:25:12Z"
      },
      "message": "ETCD Migration docu",
      "tree": {
        "sha": "ef2937b177cee96df85f5581d41465466beea398",
        "url": "https://api.github.com/repos/gardener/kubify/git/trees/ef2937b177cee96df85f5581d41465466beea398"
      },
      "url": "https://api.github.com/repos/gardener/kubify/git/commits/cd11606920cd4988e3d7a4f65d68932b061fc9ea",
      "comment_count": 0,
      "verification": {
        "verified": false,
        "reason": "unsigned",
        "signature": null,
        "payload": null
      }
    },
    "url": "https://api.github.com/repos/gardener/kubify/commits/cd11606920cd4988e3d7a4f65d68932b061fc9ea",
    "html_url": "https://github.com/gardener/kubify/commit/cd11606920cd4988e3d7a4f65d68932b061fc9ea",
    "comments_url": "https://api.github.com/repos/gardener/kubify/commits/cd11606920cd4988e3d7a4f65d68932b061fc9ea/comments",
    "author": {
      "login": "mandelsoft",
      "id": 553075,
      "node_id": "MDQ6VXNlcjU1MzA3NQ==",
      "avatar_url": "https://avatars3.githubusercontent.com/u/553075?v=4",
      "gravatar_id": "",
      "url": "https://api.github.com/users/mandelsoft",
      "html_url": "https://github.com/mandelsoft",
      "followers_url": "https://api.github.com/users/mandelsoft/followers",
      "following_url": "https://api.github.com/users/mandelsoft/following{/other_user}",
      "gists_url": "https://api.github.com/users/mandelsoft/gists{/gist_id}",
      "starred_url": "https://api.github.com/users/mandelsoft/starred{/owner}{/repo}",
      "subscriptions_url": "https://api.github.com/users/mandelsoft/subscriptions",
      "organizations_url": "https://api.github.com/users/mandelsoft/orgs",
      "repos_url": "https://api.github.com/users/mandelsoft/repos",
      "events_url": "https://api.github.com/users/mandelsoft/events{/privacy}",
      "received_events_url": "https://api.github.com/users/mandelsoft/received_events",
      "type": "User",
      "site_admin": false
    },
    "committer": {
      "login": "afritzler",
      "id": 1922939,
      "node_id": "MDQ6VXNlcjE5MjI5Mzk=",
      "avatar_url": "https://avatars2.githubusercontent.com/u/1922939?v=4",
      "gravatar_id": "",
      "url": "https://api.github.com/users/afritzler",
      "html_url": "https://github.com/afritzler",
      "followers_url": "https://api.github.com/users/afritzler/followers",
      "following_url": "https://api.github.com/users/afritzler/following{/other_user}",
      "gists_url": "https://api.github.com/users/afritzler/gists{/gist_id}",
      "starred_url": "https://api.github.com/users/afritzler/starred{/owner}{/repo}",
      "subscriptions_url": "https://api.github.com/users/afritzler/subscriptions",
      "organizations_url": "https://api.github.com/users/afritzler/orgs",
      "repos_url": "https://api.github.com/users/afritzler/repos",
      "events_url": "https://api.github.com/users/afritzler/events{/privacy}",
      "received_events_url": "https://api.github.com/users/afritzler/received_events",
      "type": "User",
      "site_admin": false
    },
    "parents": [
      {
        "sha": "b4eb60adbdffa570f888d333ecfebaaca9268915",
        "url": "https://api.github.com/repos/gardener/kubify/commits/b4eb60adbdffa570f888d333ecfebaaca9268915",
        "html_url": "https://github.com/gardener/kubify/commit/b4eb60adbdffa570f888d333ecfebaaca9268915"
      }
    ]
  },
  {
    "sha": "a3dd4b326471626ea013ccd296ca315ae717222d",
    "node_id": "MDY6Q29tbWl0MTE2NDI5NDAxOmEzZGQ0YjMyNjQ3MTYyNmVhMDEzY2NkMjk2Y2EzMTVhZTcxNzIyMmQ=",
    "commit": {
      "author": {
        "name": "Uwe Krueger",
        "email": "uwe.krueger@sap.com",
        "date": "2018-05-15T13:24:56Z"
      },
      "committer": {
        "name": "Andreas Fritzler",
        "email": "andreas.fritzler@sap.com",
        "date": "2018-10-16T15:25:12Z"
      },
      "message": "recover migration to static etcd",
      "tree": {
        "sha": "66b6cefeb393d9c42ddb7bbffc50aa1f571130d3",
        "url": "https://api.github.com/repos/gardener/kubify/git/trees/66b6cefeb393d9c42ddb7bbffc50aa1f571130d3"
      },
      "url": "https://api.github.com/repos/gardener/kubify/git/commits/a3dd4b326471626ea013ccd296ca315ae717222d",
      "comment_count": 0,
      "verification": {
        "verified": false,
        "reason": "unsigned",
        "signature": null,
        "payload": null
      }
    },
    "url": "https://api.github.com/repos/gardener/kubify/commits/a3dd4b326471626ea013ccd296ca315ae717222d",
    "html_url": "https://github.com/gardener/kubify/commit/a3dd4b326471626ea013ccd296ca315ae717222d",
    "comments_url": "https://api.github.com/repos/gardener/kubify/commits/a3dd4b326471626ea013ccd296ca315ae717222d/comments",
    "author": {
      "login": "mandelsoft",
      "id": 553075,
      "node_id": "MDQ6VXNlcjU1MzA3NQ==",
      "avatar_url": "https://avatars3.githubusercontent.com/u/553075?v=4",
      "gravatar_id": "",
      "url": "https://api.github.com/users/mandelsoft",
      "html_url": "https://github.com/mandelsoft",
      "followers_url": "https://api.github.com/users/mandelsoft/followers",
      "following_url": "https://api.github.com/users/mandelsoft/following{/other_user}",
      "gists_url": "https://api.github.com/users/mandelsoft/gists{/gist_id}",
      "starred_url": "https://api.github.com/users/mandelsoft/starred{/owner}{/repo}",
      "subscriptions_url": "https://api.github.com/users/mandelsoft/subscriptions",
      "organizations_url": "https://api.github.com/users/mandelsoft/orgs",
      "repos_url": "https://api.github.com/users/mandelsoft/repos",
      "events_url": "https://api.github.com/users/mandelsoft/events{/privacy}",
      "received_events_url": "https://api.github.com/users/mandelsoft/received_events",
      "type": "User",
      "site_admin": false
    },
    "committer": {
      "login": "afritzler",
      "id": 1922939,
      "node_id": "MDQ6VXNlcjE5MjI5Mzk=",
      "avatar_url": "https://avatars2.githubusercontent.com/u/1922939?v=4",
      "gravatar_id": "",
      "url": "https://api.github.com/users/afritzler",
      "html_url": "https://github.com/afritzler",
      "followers_url": "https://api.github.com/users/afritzler/followers",
      "following_url": "https://api.github.com/users/afritzler/following{/other_user}",
      "gists_url": "https://api.github.com/users/afritzler/gists{/gist_id}",
      "starred_url": "https://api.github.com/users/afritzler/starred{/owner}{/repo}",
      "subscriptions_url": "https://api.github.com/users/afritzler/subscriptions",
      "organizations_url": "https://api.github.com/users/afritzler/orgs",
      "repos_url": "https://api.github.com/users/afritzler/repos",
      "events_url": "https://api.github.com/users/afritzler/events{/privacy}",
      "received_events_url": "https://api.github.com/users/afritzler/received_events",
      "type": "User",
      "site_admin": false
    },
    "parents": [
      {
        "sha": "eddab3034eeb86f73e7af467e438ffb8a235a0ac",
        "url": "https://api.github.com/repos/gardener/kubify/commits/eddab3034eeb86f73e7af467e438ffb8a235a0ac",
        "html_url": "https://github.com/gardener/kubify/commit/eddab3034eeb86f73e7af467e438ffb8a235a0ac"
      }
    ]
  },
  {
    "sha": "90ec19f22c77834daa2845c3caa3c9f213a82133",
    "node_id": "MDY6Q29tbWl0MTE2NDI5NDAxOjkwZWMxOWYyMmM3NzgzNGRhYTI4NDVjM2NhYTNjOWYyMTNhODIxMzM=",
    "commit": {
      "author": {
        "name": "Onur YALAZI",
        "email": "onur@yalazi.org",
        "date": "2018-05-23T20:21:54Z"
      },
      "committer": {
        "name": "Andreas Fritzler",
        "email": "afritzler@users.noreply.github.com",
        "date": "2018-05-23T20:21:54Z"
      },
      "message": "fixed 2 typos (#39)\n\n* fixed 2 typos\r\n\r\n* just a newline",
      "tree": {
        "sha": "3f9acc75fe35440028f523050f84bfe6b201a6b6",
        "url": "https://api.github.com/repos/gardener/kubify/git/trees/3f9acc75fe35440028f523050f84bfe6b201a6b6"
      },
      "url": "https://api.github.com/repos/gardener/kubify/git/commits/90ec19f22c77834daa2845c3caa3c9f213a82133",
      "comment_count": 0,
      "verification": {
        "verified": false,
        "reason": "unsigned",
        "signature": null,
        "payload": null
      }
    },
    "url": "https://api.github.com/repos/gardener/kubify/commits/90ec19f22c77834daa2845c3caa3c9f213a82133",
    "html_url": "https://github.com/gardener/kubify/commit/90ec19f22c77834daa2845c3caa3c9f213a82133",
    "comments_url": "https://api.github.com/repos/gardener/kubify/commits/90ec19f22c77834daa2845c3caa3c9f213a82133/comments",
    "author": {
      "login": "fsniper",
      "id": 803734,
      "node_id": "MDQ6VXNlcjgwMzczNA==",
      "avatar_url": "https://avatars0.githubusercontent.com/u/803734?v=4",
      "gravatar_id": "",
      "url": "https://api.github.com/users/fsniper",
      "html_url": "https://github.com/fsniper",
      "followers_url": "https://api.github.com/users/fsniper/followers",
      "following_url": "https://api.github.com/users/fsniper/following{/other_user}",
      "gists_url": "https://api.github.com/users/fsniper/gists{/gist_id}",
      "starred_url": "https://api.github.com/users/fsniper/starred{/owner}{/repo}",
      "subscriptions_url": "https://api.github.com/users/fsniper/subscriptions",
      "organizations_url": "https://api.github.com/users/fsniper/orgs",
      "repos_url": "https://api.github.com/users/fsniper/repos",
      "events_url": "https://api.github.com/users/fsniper/events{/privacy}",
      "received_events_url": "https://api.github.com/users/fsniper/received_events",
      "type": "User",
      "site_admin": false
    },
    "committer": {
      "login": "afritzler",
      "id": 1922939,
      "node_id": "MDQ6VXNlcjE5MjI5Mzk=",
      "avatar_url": "https://avatars2.githubusercontent.com/u/1922939?v=4",
      "gravatar_id": "",
      "url": "https://api.github.com/users/afritzler",
      "html_url": "https://github.com/afritzler",
      "followers_url": "https://api.github.com/users/afritzler/followers",
      "following_url": "https://api.github.com/users/afritzler/following{/other_user}",
      "gists_url": "https://api.github.com/users/afritzler/gists{/gist_id}",
      "starred_url": "https://api.github.com/users/afritzler/starred{/owner}{/repo}",
      "subscriptions_url": "https://api.github.com/users/afritzler/subscriptions",
      "organizations_url": "https://api.github.com/users/afritzler/orgs",
      "repos_url": "https://api.github.com/users/afritzler/repos",
      "events_url": "https://api.github.com/users/afritzler/events{/privacy}",
      "received_events_url": "https://api.github.com/users/afritzler/received_events",
      "type": "User",
      "site_admin": false
    },
    "parents": [
      {
        "sha": "5481a61f7c4cb82878ee7adefdef92812c4ab412",
        "url": "https://api.github.com/repos/gardener/kubify/commits/5481a61f7c4cb82878ee7adefdef92812c4ab412",
        "html_url": "https://github.com/gardener/kubify/commit/5481a61f7c4cb82878ee7adefdef92812c4ab412"
      }
    ]
  },
  {
    "sha": "46abaef243e3d1d1f7f11b9ed037fa97ee62ec7c",
    "node_id": "MDY6Q29tbWl0MTE2NDI5NDAxOjQ2YWJhZWYyNDNlM2QxZDFmN2YxMWI5ZWQwMzdmYTk3ZWU2MmVjN2M=",
    "commit": {
      "author": {
        "name": "Uwe Krueger",
        "email": "uwe.krueger@sap.com",
        "date": "2018-03-26T15:34:22Z"
      },
      "committer": {
        "name": "Uwe Krueger",
        "email": "uwe.krueger@sap.com",
        "date": "2018-03-26T15:34:22Z"
      },
      "message": "docu for helm support",
      "tree": {
        "sha": "3f175a2aa0a4c260ff8bee6dd6c87c5cf8c5d6a2",
        "url": "https://api.github.com/repos/gardener/kubify/git/trees/3f175a2aa0a4c260ff8bee6dd6c87c5cf8c5d6a2"
      },
      "url": "https://api.github.com/repos/gardener/kubify/git/commits/46abaef243e3d1d1f7f11b9ed037fa97ee62ec7c",
      "comment_count": 0,
      "verification": {
        "verified": false,
        "reason": "unsigned",
        "signature": null,
        "payload": null
      }
    },
    "url": "https://api.github.com/repos/gardener/kubify/commits/46abaef243e3d1d1f7f11b9ed037fa97ee62ec7c",
    "html_url": "https://github.com/gardener/kubify/commit/46abaef243e3d1d1f7f11b9ed037fa97ee62ec7c",
    "comments_url": "https://api.github.com/repos/gardener/kubify/commits/46abaef243e3d1d1f7f11b9ed037fa97ee62ec7c/comments",
    "author": {
      "login": "mandelsoft",
      "id": 553075,
      "node_id": "MDQ6VXNlcjU1MzA3NQ==",
      "avatar_url": "https://avatars3.githubusercontent.com/u/553075?v=4",
      "gravatar_id": "",
      "url": "https://api.github.com/users/mandelsoft",
      "html_url": "https://github.com/mandelsoft",
      "followers_url": "https://api.github.com/users/mandelsoft/followers",
      "following_url": "https://api.github.com/users/mandelsoft/following{/other_user}",
      "gists_url": "https://api.github.com/users/mandelsoft/gists{/gist_id}",
      "starred_url": "https://api.github.com/users/mandelsoft/starred{/owner}{/repo}",
      "subscriptions_url": "https://api.github.com/users/mandelsoft/subscriptions",
      "organizations_url": "https://api.github.com/users/mandelsoft/orgs",
      "repos_url": "https://api.github.com/users/mandelsoft/repos",
      "events_url": "https://api.github.com/users/mandelsoft/events{/privacy}",
      "received_events_url": "https://api.github.com/users/mandelsoft/received_events",
      "type": "User",
      "site_admin": false
    },
    "committer": {
      "login": "mandelsoft",
      "id": 553075,
      "node_id": "MDQ6VXNlcjU1MzA3NQ==",
      "avatar_url": "https://avatars3.githubusercontent.com/u/553075?v=4",
      "gravatar_id": "",
      "url": "https://api.github.com/users/mandelsoft",
      "html_url": "https://github.com/mandelsoft",
      "followers_url": "https://api.github.com/users/mandelsoft/followers",
      "following_url": "https://api.github.com/users/mandelsoft/following{/other_user}",
      "gists_url": "https://api.github.com/users/mandelsoft/gists{/gist_id}",
      "starred_url": "https://api.github.com/users/mandelsoft/starred{/owner}{/repo}",
      "subscriptions_url": "https://api.github.com/users/mandelsoft/subscriptions",
      "organizations_url": "https://api.github.com/users/mandelsoft/orgs",
      "repos_url": "https://api.github.com/users/mandelsoft/repos",
      "events_url": "https://api.github.com/users/mandelsoft/events{/privacy}",
      "received_events_url": "https://api.github.com/users/mandelsoft/received_events",
      "type": "User",
      "site_admin": false
    },
    "parents": [
      {
        "sha": "16f0aa86f8eb2f5c399a2fd3945ecf834e2d411d",
        "url": "https://api.github.com/repos/gardener/kubify/commits/16f0aa86f8eb2f5c399a2fd3945ecf834e2d411d",
        "html_url": "https://github.com/gardener/kubify/commit/16f0aa86f8eb2f5c399a2fd3945ecf834e2d411d"
      }
    ]
  },
  {
    "sha": "b52a9756a054a0e4726b14dd1ccd293b96abc15d",
    "node_id": "MDY6Q29tbWl0MTE2NDI5NDAxOmI1MmE5NzU2YTA1NGEwZTQ3MjZiMTRkZDFjY2QyOTNiOTZhYmMxNWQ=",
    "commit": {
      "author": {
        "name": "Vedran Lerenc",
        "email": "vedran.lerenc@sap.com",
        "date": "2018-03-07T11:44:33Z"
      },
      "committer": {
        "name": "Vedran Lerenc",
        "email": "vedran.lerenc@sap.com",
        "date": "2018-03-07T11:44:33Z"
      },
      "message": "Update logo",
      "tree": {
        "sha": "e7ba942b68f11a321713695a75326dd6af572b6b",
        "url": "https://api.github.com/repos/gardener/kubify/git/trees/e7ba942b68f11a321713695a75326dd6af572b6b"
      },
      "url": "https://api.github.com/repos/gardener/kubify/git/commits/b52a9756a054a0e4726b14dd1ccd293b96abc15d",
      "comment_count": 0,
      "verification": {
        "verified": false,
        "reason": "unsigned",
        "signature": null,
        "payload": null
      }
    },
    "url": "https://api.github.com/repos/gardener/kubify/commits/b52a9756a054a0e4726b14dd1ccd293b96abc15d",
    "html_url": "https://github.com/gardener/kubify/commit/b52a9756a054a0e4726b14dd1ccd293b96abc15d",
    "comments_url": "https://api.github.com/repos/gardener/kubify/commits/b52a9756a054a0e4726b14dd1ccd293b96abc15d/comments",
    "author": {
      "login": "vlerenc",
      "id": 4974203,
      "node_id": "MDQ6VXNlcjQ5NzQyMDM=",
      "avatar_url": "https://avatars1.githubusercontent.com/u/4974203?v=4",
      "gravatar_id": "",
      "url": "https://api.github.com/users/vlerenc",
      "html_url": "https://github.com/vlerenc",
      "followers_url": "https://api.github.com/users/vlerenc/followers",
      "following_url": "https://api.github.com/users/vlerenc/following{/other_user}",
      "gists_url": "https://api.github.com/users/vlerenc/gists{/gist_id}",
      "starred_url": "https://api.github.com/users/vlerenc/starred{/owner}{/repo}",
      "subscriptions_url": "https://api.github.com/users/vlerenc/subscriptions",
      "organizations_url": "https://api.github.com/users/vlerenc/orgs",
      "repos_url": "https://api.github.com/users/vlerenc/repos",
      "events_url": "https://api.github.com/users/vlerenc/events{/privacy}",
      "received_events_url": "https://api.github.com/users/vlerenc/received_events",
      "type": "User",
      "site_admin": false
    },
    "committer": {
      "login": "vlerenc",
      "id": 4974203,
      "node_id": "MDQ6VXNlcjQ5NzQyMDM=",
      "avatar_url": "https://avatars1.githubusercontent.com/u/4974203?v=4",
      "gravatar_id": "",
      "url": "https://api.github.com/users/vlerenc",
      "html_url": "https://github.com/vlerenc",
      "followers_url": "https://api.github.com/users/vlerenc/followers",
      "following_url": "https://api.github.com/users/vlerenc/following{/other_user}",
      "gists_url": "https://api.github.com/users/vlerenc/gists{/gist_id}",
      "starred_url": "https://api.github.com/users/vlerenc/starred{/owner}{/repo}",
      "subscriptions_url": "https://api.github.com/users/vlerenc/subscriptions",
      "organizations_url": "https://api.github.com/users/vlerenc/orgs",
      "repos_url": "https://api.github.com/users/vlerenc/repos",
      "events_url": "https://api.github.com/users/vlerenc/events{/privacy}",
      "received_events_url": "https://api.github.com/users/vlerenc/received_events",
      "type": "User",
      "site_admin": false
    },
    "parents": [
      {
        "sha": "69f95808252bd6822f2dfe723f41a50b8e71b701",
        "url": "https://api.github.com/repos/gardener/kubify/commits/69f95808252bd6822f2dfe723f41a50b8e71b701",
        "html_url": "https://github.com/gardener/kubify/commit/69f95808252bd6822f2dfe723f41a50b8e71b701"
      }
    ]
  },
  {
    "sha": "b3662468ad4e1484cf6e4f9b398096e09e36b126",
    "node_id": "MDY6Q29tbWl0MTE2NDI5NDAxOmIzNjYyNDY4YWQ0ZTE0ODRjZjZlNGY5YjM5ODA5NmUwOWUzNmIxMjY=",
    "commit": {
      "author": {
        "name": "Uwe Krueger",
        "email": "uwe.krueger@sap.com",
        "date": "2018-01-30T14:30:56Z"
      },
      "committer": {
        "name": "Uwe Krueger",
        "email": "uwe.krueger@sap.com",
        "date": "2018-01-31T14:36:59Z"
      },
      "message": "dex identity addon",
      "tree": {
        "sha": "54ffd2c62e110f796a70f6a496207a8c6b3ec912",
        "url": "https://api.github.com/repos/gardener/kubify/git/trees/54ffd2c62e110f796a70f6a496207a8c6b3ec912"
      },
      "url": "https://api.github.com/repos/gardener/kubify/git/commits/b3662468ad4e1484cf6e4f9b398096e09e36b126",
      "comment_count": 0,
      "verification": {
        "verified": false,
        "reason": "unsigned",
        "signature": null,
        "payload": null
      }
    },
    "url": "https://api.github.com/repos/gardener/kubify/commits/b3662468ad4e1484cf6e4f9b398096e09e36b126",
    "html_url": "https://github.com/gardener/kubify/commit/b3662468ad4e1484cf6e4f9b398096e09e36b126",
    "comments_url": "https://api.github.com/repos/gardener/kubify/commits/b3662468ad4e1484cf6e4f9b398096e09e36b126/comments",
    "author": {
      "login": "mandelsoft",
      "id": 553075,
      "node_id": "MDQ6VXNlcjU1MzA3NQ==",
      "avatar_url": "https://avatars3.githubusercontent.com/u/553075?v=4",
      "gravatar_id": "",
      "url": "https://api.github.com/users/mandelsoft",
      "html_url": "https://github.com/mandelsoft",
      "followers_url": "https://api.github.com/users/mandelsoft/followers",
      "following_url": "https://api.github.com/users/mandelsoft/following{/other_user}",
      "gists_url": "https://api.github.com/users/mandelsoft/gists{/gist_id}",
      "starred_url": "https://api.github.com/users/mandelsoft/starred{/owner}{/repo}",
      "subscriptions_url": "https://api.github.com/users/mandelsoft/subscriptions",
      "organizations_url": "https://api.github.com/users/mandelsoft/orgs",
      "repos_url": "https://api.github.com/users/mandelsoft/repos",
      "events_url": "https://api.github.com/users/mandelsoft/events{/privacy}",
      "received_events_url": "https://api.github.com/users/mandelsoft/received_events",
      "type": "User",
      "site_admin": false
    },
    "committer": {
      "login": "mandelsoft",
      "id": 553075,
      "node_id": "MDQ6VXNlcjU1MzA3NQ==",
      "avatar_url": "https://avatars3.githubusercontent.com/u/553075?v=4",
      "gravatar_id": "",
      "url": "https://api.github.com/users/mandelsoft",
      "html_url": "https://github.com/mandelsoft",
      "followers_url": "https://api.github.com/users/mandelsoft/followers",
      "following_url": "https://api.github.com/users/mandelsoft/following{/other_user}",
      "gists_url": "https://api.github.com/users/mandelsoft/gists{/gist_id}",
      "starred_url": "https://api.github.com/users/mandelsoft/starred{/owner}{/repo}",
      "subscriptions_url": "https://api.github.com/users/mandelsoft/subscriptions",
      "organizations_url": "https://api.github.com/users/mandelsoft/orgs",
      "repos_url": "https://api.github.com/users/mandelsoft/repos",
      "events_url": "https://api.github.com/users/mandelsoft/events{/privacy}",
      "received_events_url": "https://api.github.com/users/mandelsoft/received_events",
      "type": "User",
      "site_admin": false
    },
    "parents": [
      {
        "sha": "b3008e620d649439f230418f3997aedf8b539af0",
        "url": "https://api.github.com/repos/gardener/kubify/commits/b3008e620d649439f230418f3997aedf8b539af0",
        "html_url": "https://github.com/gardener/kubify/commit/b3008e620d649439f230418f3997aedf8b539af0"
      }
    ]
  },
  {
    "sha": "842cd54cc7f166e8291b3fee4482fc23fc360a52",
    "node_id": "MDY6Q29tbWl0MTE2NDI5NDAxOjg0MmNkNTRjYzdmMTY2ZTgyOTFiM2ZlZTQ0ODJmYzIzZmMzNjBhNTI=",
    "commit": {
      "author": {
        "name": "Uwe Krueger",
        "email": "uwe.krueger@sap.com",
        "date": "2018-01-26T13:36:17Z"
      },
      "committer": {
        "name": "Uwe Krueger",
        "email": "uwe.krueger@sap.com",
        "date": "2018-01-26T15:23:15Z"
      },
      "message": "Configurable root volume size",
      "tree": {
        "sha": "d80a9f02174a2cd18f03117d25c3f1dee82b2dab",
        "url": "https://api.github.com/repos/gardener/kubify/git/trees/d80a9f02174a2cd18f03117d25c3f1dee82b2dab"
      },
      "url": "https://api.github.com/repos/gardener/kubify/git/commits/842cd54cc7f166e8291b3fee4482fc23fc360a52",
      "comment_count": 0,
      "verification": {
        "verified": false,
        "reason": "unsigned",
        "signature": null,
        "payload": null
      }
    },
    "url": "https://api.github.com/repos/gardener/kubify/commits/842cd54cc7f166e8291b3fee4482fc23fc360a52",
    "html_url": "https://github.com/gardener/kubify/commit/842cd54cc7f166e8291b3fee4482fc23fc360a52",
    "comments_url": "https://api.github.com/repos/gardener/kubify/commits/842cd54cc7f166e8291b3fee4482fc23fc360a52/comments",
    "author": {
      "login": "mandelsoft",
      "id": 553075,
      "node_id": "MDQ6VXNlcjU1MzA3NQ==",
      "avatar_url": "https://avatars3.githubusercontent.com/u/553075?v=4",
      "gravatar_id": "",
      "url": "https://api.github.com/users/mandelsoft",
      "html_url": "https://github.com/mandelsoft",
      "followers_url": "https://api.github.com/users/mandelsoft/followers",
      "following_url": "https://api.github.com/users/mandelsoft/following{/other_user}",
      "gists_url": "https://api.github.com/users/mandelsoft/gists{/gist_id}",
      "starred_url": "https://api.github.com/users/mandelsoft/starred{/owner}{/repo}",
      "subscriptions_url": "https://api.github.com/users/mandelsoft/subscriptions",
      "organizations_url": "https://api.github.com/users/mandelsoft/orgs",
      "repos_url": "https://api.github.com/users/mandelsoft/repos",
      "events_url": "https://api.github.com/users/mandelsoft/events{/privacy}",
      "received_events_url": "https://api.github.com/users/mandelsoft/received_events",
      "type": "User",
      "site_admin": false
    },
    "committer": {
      "login": "mandelsoft",
      "id": 553075,
      "node_id": "MDQ6VXNlcjU1MzA3NQ==",
      "avatar_url": "https://avatars3.githubusercontent.com/u/553075?v=4",
      "gravatar_id": "",
      "url": "https://api.github.com/users/mandelsoft",
      "html_url": "https://github.com/mandelsoft",
      "followers_url": "https://api.github.com/users/mandelsoft/followers",
      "following_url": "https://api.github.com/users/mandelsoft/following{/other_user}",
      "gists_url": "https://api.github.com/users/mandelsoft/gists{/gist_id}",
      "starred_url": "https://api.github.com/users/mandelsoft/starred{/owner}{/repo}",
      "subscriptions_url": "https://api.github.com/users/mandelsoft/subscriptions",
      "organizations_url": "https://api.github.com/users/mandelsoft/orgs",
      "repos_url": "https://api.github.com/users/mandelsoft/repos",
      "events_url": "https://api.github.com/users/mandelsoft/events{/privacy}",
      "received_events_url": "https://api.github.com/users/mandelsoft/received_events",
      "type": "User",
      "site_admin": false
    },
    "parents": [
      {
        "sha": "7ca2cc84fc0f3a1153bbef5c7a951b888008165e",
        "url": "https://api.github.com/repos/gardener/kubify/commits/7ca2cc84fc0f3a1153bbef5c7a951b888008165e",
        "html_url": "https://github.com/gardener/kubify/commit/7ca2cc84fc0f3a1153bbef5c7a951b888008165e"
      }
    ]
  },
  {
    "sha": "d0016d9dd1804300e3e695888562ecba727ca42f",
    "node_id": "MDY6Q29tbWl0MTE2NDI5NDAxOmQwMDE2ZDlkZDE4MDQzMDBlM2U2OTU4ODg1NjJlY2JhNzI3Y2E0MmY=",
    "commit": {
      "author": {
        "name": "Uwe Krueger",
        "email": "uwe.krueger@sap.com",
        "date": "2018-01-15T15:23:37Z"
      },
      "committer": {
        "name": "Uwe Krueger",
        "email": "uwe.krueger@sap.com",
        "date": "2018-01-17T10:27:33Z"
      },
      "message": "INCOMPATIBLE: move main module\n\nThe main cluster modules have been moved from the root\nof the project to a regular module (instance) in the\nmodules folder.\nThis is incompatible. A state migration cannot be defined\nbecause terraform cannot handle the move of template\nresources. This type of resource saves absolute path names\nin the state (never a good idea). These are not valid\nanymore, if the resource is moved.",
      "tree": {
        "sha": "249b5bdf91e82465fea3734c18a47220326bc951",
        "url": "https://api.github.com/repos/gardener/kubify/git/trees/249b5bdf91e82465fea3734c18a47220326bc951"
      },
      "url": "https://api.github.com/repos/gardener/kubify/git/commits/d0016d9dd1804300e3e695888562ecba727ca42f",
      "comment_count": 0,
      "verification": {
        "verified": false,
        "reason": "unsigned",
        "signature": null,
        "payload": null
      }
    },
    "url": "https://api.github.com/repos/gardener/kubify/commits/d0016d9dd1804300e3e695888562ecba727ca42f",
    "html_url": "https://github.com/gardener/kubify/commit/d0016d9dd1804300e3e695888562ecba727ca42f",
    "comments_url": "https://api.github.com/repos/gardener/kubify/commits/d0016d9dd1804300e3e695888562ecba727ca42f/comments",
    "author": {
      "login": "mandelsoft",
      "id": 553075,
      "node_id": "MDQ6VXNlcjU1MzA3NQ==",
      "avatar_url": "https://avatars3.githubusercontent.com/u/553075?v=4",
      "gravatar_id": "",
      "url": "https://api.github.com/users/mandelsoft",
      "html_url": "https://github.com/mandelsoft",
      "followers_url": "https://api.github.com/users/mandelsoft/followers",
      "following_url": "https://api.github.com/users/mandelsoft/following{/other_user}",
      "gists_url": "https://api.github.com/users/mandelsoft/gists{/gist_id}",
      "starred_url": "https://api.github.com/users/mandelsoft/starred{/owner}{/repo}",
      "subscriptions_url": "https://api.github.com/users/mandelsoft/subscriptions",
      "organizations_url": "https://api.github.com/users/mandelsoft/orgs",
      "repos_url": "https://api.github.com/users/mandelsoft/repos",
      "events_url": "https://api.github.com/users/mandelsoft/events{/privacy}",
      "received_events_url": "https://api.github.com/users/mandelsoft/received_events",
      "type": "User",
      "site_admin": false
    },
    "committer": {
      "login": "mandelsoft",
      "id": 553075,
      "node_id": "MDQ6VXNlcjU1MzA3NQ==",
      "avatar_url": "https://avatars3.githubusercontent.com/u/553075?v=4",
      "gravatar_id": "",
      "url": "https://api.github.com/users/mandelsoft",
      "html_url": "https://github.com/mandelsoft",
      "followers_url": "https://api.github.com/users/mandelsoft/followers",
      "following_url": "https://api.github.com/users/mandelsoft/following{/other_user}",
      "gists_url": "https://api.github.com/users/mandelsoft/gists{/gist_id}",
      "starred_url": "https://api.github.com/users/mandelsoft/starred{/owner}{/repo}",
      "subscriptions_url": "https://api.github.com/users/mandelsoft/subscriptions",
      "organizations_url": "https://api.github.com/users/mandelsoft/orgs",
      "repos_url": "https://api.github.com/users/mandelsoft/repos",
      "events_url": "https://api.github.com/users/mandelsoft/events{/privacy}",
      "received_events_url": "https://api.github.com/users/mandelsoft/received_events",
      "type": "User",
      "site_admin": false
    },
    "parents": [
      {
        "sha": "bde8b26826b6930b223c6885d693f533a8de4b7a",
        "url": "https://api.github.com/repos/gardener/kubify/commits/bde8b26826b6930b223c6885d693f533a8de4b7a",
        "html_url": "https://github.com/gardener/kubify/commit/bde8b26826b6930b223c6885d693f533a8de4b7a"
      }
    ]
  },
  {
    "sha": "b65941b5c463af2e2e2400a0a904c613e5efe661",
    "node_id": "MDY6Q29tbWl0MTE2NDI5NDAxOmI2NTk0MWI1YzQ2M2FmMmUyZTI0MDBhMGE5MDRjNjEzZTVlZmU2NjE=",
    "commit": {
      "author": {
        "name": "Andreas Fritzler",
        "email": "andreas.fritzler@sap.com",
        "date": "2018-01-15T09:51:43Z"
      },
      "committer": {
        "name": "Matthias Sohn",
        "email": "matthias.sohn@sap.com",
        "date": "2018-01-17T00:33:50Z"
      },
      "message": "Generalized sample OpenStack configuration",
      "tree": {
        "sha": "f71601eb9fa1dd317755cdf8ed0b673b9b37de69",
        "url": "https://api.github.com/repos/gardener/kubify/git/trees/f71601eb9fa1dd317755cdf8ed0b673b9b37de69"
      },
      "url": "https://api.github.com/repos/gardener/kubify/git/commits/b65941b5c463af2e2e2400a0a904c613e5efe661",
      "comment_count": 0,
      "verification": {
        "verified": false,
        "reason": "unsigned",
        "signature": null,
        "payload": null
      }
    },
    "url": "https://api.github.com/repos/gardener/kubify/commits/b65941b5c463af2e2e2400a0a904c613e5efe661",
    "html_url": "https://github.com/gardener/kubify/commit/b65941b5c463af2e2e2400a0a904c613e5efe661",
    "comments_url": "https://api.github.com/repos/gardener/kubify/commits/b65941b5c463af2e2e2400a0a904c613e5efe661/comments",
    "author": {
      "login": "afritzler",
      "id": 1922939,
      "node_id": "MDQ6VXNlcjE5MjI5Mzk=",
      "avatar_url": "https://avatars2.githubusercontent.com/u/1922939?v=4",
      "gravatar_id": "",
      "url": "https://api.github.com/users/afritzler",
      "html_url": "https://github.com/afritzler",
      "followers_url": "https://api.github.com/users/afritzler/followers",
      "following_url": "https://api.github.com/users/afritzler/following{/other_user}",
      "gists_url": "https://api.github.com/users/afritzler/gists{/gist_id}",
      "starred_url": "https://api.github.com/users/afritzler/starred{/owner}{/repo}",
      "subscriptions_url": "https://api.github.com/users/afritzler/subscriptions",
      "organizations_url": "https://api.github.com/users/afritzler/orgs",
      "repos_url": "https://api.github.com/users/afritzler/repos",
      "events_url": "https://api.github.com/users/afritzler/events{/privacy}",
      "received_events_url": "https://api.github.com/users/afritzler/received_events",
      "type": "User",
      "site_admin": false
    },
    "committer": {
      "login": "msohn",
      "id": 143355,
      "node_id": "MDQ6VXNlcjE0MzM1NQ==",
      "avatar_url": "https://avatars0.githubusercontent.com/u/143355?v=4",
      "gravatar_id": "",
      "url": "https://api.github.com/users/msohn",
      "html_url": "https://github.com/msohn",
      "followers_url": "https://api.github.com/users/msohn/followers",
      "following_url": "https://api.github.com/users/msohn/following{/other_user}",
      "gists_url": "https://api.github.com/users/msohn/gists{/gist_id}",
      "starred_url": "https://api.github.com/users/msohn/starred{/owner}{/repo}",
      "subscriptions_url": "https://api.github.com/users/msohn/subscriptions",
      "organizations_url": "https://api.github.com/users/msohn/orgs",
      "repos_url": "https://api.github.com/users/msohn/repos",
      "events_url": "https://api.github.com/users/msohn/events{/privacy}",
      "received_events_url": "https://api.github.com/users/msohn/received_events",
      "type": "User",
      "site_admin": false
    },
    "parents": [
      {
        "sha": "7cc905aec9080ca8a758fe24683b38d4f2e2394f",
        "url": "https://api.github.com/repos/gardener/kubify/commits/7cc905aec9080ca8a758fe24683b38d4f2e2394f",
        "html_url": "https://github.com/gardener/kubify/commit/7cc905aec9080ca8a758fe24683b38d4f2e2394f"
      }
    ]
  },
  {
    "sha": "7cc905aec9080ca8a758fe24683b38d4f2e2394f",
    "node_id": "MDY6Q29tbWl0MTE2NDI5NDAxOjdjYzkwNWFlYzkwODBjYThhNzU4ZmUyNDY4M2IzOGQ0ZjJlMjM5NGY=",
    "commit": {
      "author": {
        "name": "Andreas Fritzler",
        "email": "andreas.fritzler@sap.com",
        "date": "2018-01-15T09:46:46Z"
      },
      "committer": {
        "name": "Matthias Sohn",
        "email": "matthias.sohn@sap.com",
        "date": "2018-01-17T00:33:50Z"
      },
      "message": "Updated repo links in readme",
      "tree": {
        "sha": "828145dccab364f879477243844a3801097eb8b2",
        "url": "https://api.github.com/repos/gardener/kubify/git/trees/828145dccab364f879477243844a3801097eb8b2"
      },
      "url": "https://api.github.com/repos/gardener/kubify/git/commits/7cc905aec9080ca8a758fe24683b38d4f2e2394f",
      "comment_count": 0,
      "verification": {
        "verified": false,
        "reason": "unsigned",
        "signature": null,
        "payload": null
      }
    },
    "url": "https://api.github.com/repos/gardener/kubify/commits/7cc905aec9080ca8a758fe24683b38d4f2e2394f",
    "html_url": "https://github.com/gardener/kubify/commit/7cc905aec9080ca8a758fe24683b38d4f2e2394f",
    "comments_url": "https://api.github.com/repos/gardener/kubify/commits/7cc905aec9080ca8a758fe24683b38d4f2e2394f/comments",
    "author": {
      "login": "afritzler",
      "id": 1922939,
      "node_id": "MDQ6VXNlcjE5MjI5Mzk=",
      "avatar_url": "https://avatars2.githubusercontent.com/u/1922939?v=4",
      "gravatar_id": "",
      "url": "https://api.github.com/users/afritzler",
      "html_url": "https://github.com/afritzler",
      "followers_url": "https://api.github.com/users/afritzler/followers",
      "following_url": "https://api.github.com/users/afritzler/following{/other_user}",
      "gists_url": "https://api.github.com/users/afritzler/gists{/gist_id}",
      "starred_url": "https://api.github.com/users/afritzler/starred{/owner}{/repo}",
      "subscriptions_url": "https://api.github.com/users/afritzler/subscriptions",
      "organizations_url": "https://api.github.com/users/afritzler/orgs",
      "repos_url": "https://api.github.com/users/afritzler/repos",
      "events_url": "https://api.github.com/users/afritzler/events{/privacy}",
      "received_events_url": "https://api.github.com/users/afritzler/received_events",
      "type": "User",
      "site_admin": false
    },
    "committer": {
      "login": "msohn",
      "id": 143355,
      "node_id": "MDQ6VXNlcjE0MzM1NQ==",
      "avatar_url": "https://avatars0.githubusercontent.com/u/143355?v=4",
      "gravatar_id": "",
      "url": "https://api.github.com/users/msohn",
      "html_url": "https://github.com/msohn",
      "followers_url": "https://api.github.com/users/msohn/followers",
      "following_url": "https://api.github.com/users/msohn/following{/other_user}",
      "gists_url": "https://api.github.com/users/msohn/gists{/gist_id}",
      "starred_url": "https://api.github.com/users/msohn/starred{/owner}{/repo}",
      "subscriptions_url": "https://api.github.com/users/msohn/subscriptions",
      "organizations_url": "https://api.github.com/users/msohn/orgs",
      "repos_url": "https://api.github.com/users/msohn/repos",
      "events_url": "https://api.github.com/users/msohn/events{/privacy}",
      "received_events_url": "https://api.github.com/users/msohn/received_events",
      "type": "User",
      "site_admin": false
    },
    "parents": [
      {
        "sha": "49800ed50dc3a0aedd733c0a3bf3d2899d56e0ce",
        "url": "https://api.github.com/repos/gardener/kubify/commits/49800ed50dc3a0aedd733c0a3bf3d2899d56e0ce",
        "html_url": "https://github.com/gardener/kubify/commit/49800ed50dc3a0aedd733c0a3bf3d2899d56e0ce"
      }
    ]
  },
  {
    "sha": "70a7105b113af8ba0e485e56135a88b82654c953",
    "node_id": "MDY6Q29tbWl0MTE2NDI5NDAxOjcwYTcxMDViMTEzYWY4YmEwZTQ4NWU1NjEzNWE4OGI4MjY1NGM5NTM=",
    "commit": {
      "author": {
        "name": "Uwe Krueger",
        "email": "uwe.krueger@sap.com",
        "date": "2018-01-05T21:44:58Z"
      },
      "committer": {
        "name": "Matthias Sohn",
        "email": "matthias.sohn@sap.com",
        "date": "2018-01-17T00:33:49Z"
      },
      "message": "align bastion with master and worker",
      "tree": {
        "sha": "5eaec3ff826f3d8c61a96a6f60423b7591cfe3d8",
        "url": "https://api.github.com/repos/gardener/kubify/git/trees/5eaec3ff826f3d8c61a96a6f60423b7591cfe3d8"
      },
      "url": "https://api.github.com/repos/gardener/kubify/git/commits/70a7105b113af8ba0e485e56135a88b82654c953",
      "comment_count": 0,
      "verification": {
        "verified": false,
        "reason": "unsigned",
        "signature": null,
        "payload": null
      }
    },
    "url": "https://api.github.com/repos/gardener/kubify/commits/70a7105b113af8ba0e485e56135a88b82654c953",
    "html_url": "https://github.com/gardener/kubify/commit/70a7105b113af8ba0e485e56135a88b82654c953",
    "comments_url": "https://api.github.com/repos/gardener/kubify/commits/70a7105b113af8ba0e485e56135a88b82654c953/comments",
    "author": {
      "login": "mandelsoft",
      "id": 553075,
      "node_id": "MDQ6VXNlcjU1MzA3NQ==",
      "avatar_url": "https://avatars3.githubusercontent.com/u/553075?v=4",
      "gravatar_id": "",
      "url": "https://api.github.com/users/mandelsoft",
      "html_url": "https://github.com/mandelsoft",
      "followers_url": "https://api.github.com/users/mandelsoft/followers",
      "following_url": "https://api.github.com/users/mandelsoft/following{/other_user}",
      "gists_url": "https://api.github.com/users/mandelsoft/gists{/gist_id}",
      "starred_url": "https://api.github.com/users/mandelsoft/starred{/owner}{/repo}",
      "subscriptions_url": "https://api.github.com/users/mandelsoft/subscriptions",
      "organizations_url": "https://api.github.com/users/mandelsoft/orgs",
      "repos_url": "https://api.github.com/users/mandelsoft/repos",
      "events_url": "https://api.github.com/users/mandelsoft/events{/privacy}",
      "received_events_url": "https://api.github.com/users/mandelsoft/received_events",
      "type": "User",
      "site_admin": false
    },
    "committer": {
      "login": "msohn",
      "id": 143355,
      "node_id": "MDQ6VXNlcjE0MzM1NQ==",
      "avatar_url": "https://avatars0.githubusercontent.com/u/143355?v=4",
      "gravatar_id": "",
      "url": "https://api.github.com/users/msohn",
      "html_url": "https://github.com/msohn",
      "followers_url": "https://api.github.com/users/msohn/followers",
      "following_url": "https://api.github.com/users/msohn/following{/other_user}",
      "gists_url": "https://api.github.com/users/msohn/gists{/gist_id}",
      "starred_url": "https://api.github.com/users/msohn/starred{/owner}{/repo}",
      "subscriptions_url": "https://api.github.com/users/msohn/subscriptions",
      "organizations_url": "https://api.github.com/users/msohn/orgs",
      "repos_url": "https://api.github.com/users/msohn/repos",
      "events_url": "https://api.github.com/users/msohn/events{/privacy}",
      "received_events_url": "https://api.github.com/users/msohn/received_events",
      "type": "User",
      "site_admin": false
    },
    "parents": [
      {
        "sha": "1b5d44720d61fbbd7cd720ff62da990015cfda7c",
        "url": "https://api.github.com/repos/gardener/kubify/commits/1b5d44720d61fbbd7cd720ff62da990015cfda7c",
        "html_url": "https://github.com/gardener/kubify/commit/1b5d44720d61fbbd7cd720ff62da990015cfda7c"
      }
    ]
  },
  {
    "sha": "31747a476dcc6ddd7881904ac394207328ad61bc",
    "node_id": "MDY6Q29tbWl0MTE2NDI5NDAxOjMxNzQ3YTQ3NmRjYzZkZGQ3ODgxOTA0YWMzOTQyMDczMjhhZDYxYmM=",
    "commit": {
      "author": {
        "name": "Gardener Development Community",
        "email": "gardener.opensource@sap.com",
        "date": "2018-01-04T11:47:22Z"
      },
      "committer": {
        "name": "Matthias Sohn",
        "email": "matthias.sohn@sap.com",
        "date": "2018-01-17T00:30:42Z"
      },
      "message": "Initial version of kubify\n\nThis is the initial contribution to the Open Source Gardener project.\n\nThe following SAP developers contributed to this project until this\ninitial contribution was published as open source:\n\n$ git shortlog -sn\n   103  Uwe Krueger\n    35  Andreas Fritzler\n     4  Matthias Sohn\n     2  Daniel Gonzalez\n     1  Michael Sprauer\n\nIt is derived from the historical, SAP internal kubify repository\nat commit e521221ba511da6cd2a208615481fc1da698e2b7.",
      "tree": {
        "sha": "449ade4b1c5c39294aac52322636afbd6eff456c",
        "url": "https://api.github.com/repos/gardener/kubify/git/trees/449ade4b1c5c39294aac52322636afbd6eff456c"
      },
      "url": "https://api.github.com/repos/gardener/kubify/git/commits/31747a476dcc6ddd7881904ac394207328ad61bc",
      "comment_count": 0,
      "verification": {
        "verified": false,
        "reason": "unsigned",
        "signature": null,
        "payload": null
      }
    },
    "url": "https://api.github.com/repos/gardener/kubify/commits/31747a476dcc6ddd7881904ac394207328ad61bc",
    "html_url": "https://github.com/gardener/kubify/commit/31747a476dcc6ddd7881904ac394207328ad61bc",
    "comments_url": "https://api.github.com/repos/gardener/kubify/commits/31747a476dcc6ddd7881904ac394207328ad61bc/comments",
    "author": null,
    "committer": {
      "login": "msohn",
      "id": 143355,
      "node_id": "MDQ6VXNlcjE0MzM1NQ==",
      "avatar_url": "https://avatars0.githubusercontent.com/u/143355?v=4",
      "gravatar_id": "",
      "url": "https://api.github.com/users/msohn",
      "html_url": "https://github.com/msohn",
      "followers_url": "https://api.github.com/users/msohn/followers",
      "following_url": "https://api.github.com/users/msohn/following{/other_user}",
      "gists_url": "https://api.github.com/users/msohn/gists{/gist_id}",
      "starred_url": "https://api.github.com/users/msohn/starred{/owner}{/repo}",
      "subscriptions_url": "https://api.github.com/users/msohn/subscriptions",
      "organizations_url": "https://api.github.com/users/msohn/orgs",
      "repos_url": "https://api.github.com/users/msohn/repos",
      "events_url": "https://api.github.com/users/msohn/events{/privacy}",
      "received_events_url": "https://api.github.com/users/msohn/received_events",
      "type": "User",
      "site_admin": false
    },
    "parents": []
  }
]